{
  "dealer": {
    "symbols": {
      "UNI/USDT": [
        "ascendex",
        "bequant",
        "binance",
        "bingx",
        "bitfinex2",
        "bitget",
        "bitmart",
        "bitmex",
        "bitrue",
        "blockchaincom",
        "bybit",
        "cex",
        "coinex",
        "cryptocom",
        "currencycom",
        "exmo",
        "gate",
        "hitbtc",
        "hollaex",
        "htx",
        "kucoin",
        "lbank",
        "mexc",
        "okx",
        "phemex",
        "poloniex",
        "probit",
        "wazirx",
        "whitebit",
        "woo"
      ],
      "SEI/USDT": [
        "binance",
        "bingx",
        "bitfinex2",
        "bitget",
        "bitmart",
        "bitrue",
        "bybit",
        "cex",
        "coinex",
        "cryptocom",
        "gate",
        "hitbtc",
        "htx",
        "kucoin",
        "lbank",
        "mexc",
        "phemex",
        "wazirx",
        "whitebit"
      ],
      "RAY/USDT": [
        "binance",
        "bingx",
        "bitget",
        "bitmart",
        "bitrue",
        "coinex",
        "gate",
        "hitbtc",
        "kucoin",
        "lbank",
        "mexc",
        "okx",
        "phemex",
        "poloniex",
        "probit",
        "wazirx",
        "woo"
      ],
      "BAT/USDT": [
        "ascendex",
        "bequant",
        "binance",
        "bingx",
        "bitget",
        "bitmart",
        "bitrue",
        "blockchaincom",
        "bybit",
        "cex",
        "coinex",
        "cryptocom",
        "gate",
        "hitbtc",
        "htx",
        "kucoin",
        "mexc",
        "okx",
        "p2b",
        "phemex",
        "poloniex",
        "probit",
        "upbit",
        "wazirx",
        "whitebit"
      ]
    }
  },
  "updater": [
    {
      "exchange": "bitmart",
      "mode": "batch",
      "method": "watchOrderBookForSymbols",
      "symbols": [
        "LTC/USDT",
        "BTT/USDT",
        "NOT/USDT",
        "JASMY/USDT",
        "MNT/USDT",
        "BICO/USDT",
        "KLAY/USDT",
        "BCH/USDT",
        "ASTR/USDT",
        "CELO/USDT",
        "EOS/USDT",
        "GNO/USDT",
        "ARKM/USDT",
        "AAVE/USDT",
        "JST/USDT",
        "XTZ/USDT",
        "DYM/USDT",
        "1INCH/USDT",
        "SUPER/USDT",
        "DYDX/USDT"
      ],
      "limit": 20
    },
    {
      "exchange": "mexc",
      "mode": "single",
      "method": "fetchOrderBook",
      "symbols": [
        "AAVE/USDT"
      ],
      "limit": null
    },
    {
      "exchange": "bitrue",
      "mode": "single",
      "method": "fetchOrderBook",
      "symbols": [
        "ALGO/USDT"
      ],
      "limit": null
    },
    {
      "exchange": "bingx",
      "mode": "single",
      "method": "fetchOrderBook",
      "symbols": [
        "ANT/USDT"
      ],
      "limit": null
    },
    {
      "exchange": "bitfinex2",
      "mode": "single",
      "method": "fetchOrderBook",
      "symbols": [
        "ARB/USDT"
      ],
      "limit": null
    },
    {
      "exchange": "phemex",
      "mode": "single",
      "method": "fetchOrderBook",
      "symbols": [
        "ATOM/USDT"
      ],
      "limit": null
    },
    {
      "exchange": "blockchaincom",
      "mode": "single",
      "method": "fetchOrderBook",
      "symbols": [
        "BAT/USDT"
      ],
      "limit": null
    },
    {
      "exchange": "ascendex",
      "mode": "single",
      "method": "fetchOrderBook",
      "symbols": [
        "BLUR/USDT"
      ],
      "limit": null
    },
    {
      "exchange": "gate",
      "mode": "single",
      "method": "fetchOrderBook",
      "symbols": [
        "BRETT/USDT"
      ],
      "limit": null
    },
    {
      "exchange": "probit",
      "mode": "single",
      "method": "fetchOrderBook",
      "symbols": [
        "CAKE/USDT"
      ],
      "limit": null
    },
    {
      "exchange": "bitrue",
      "mode": "single",
      "method": "fetchOrderBook",
      "symbols": [
        "CKB/USDT"
      ],
      "limit": null
    },
    {
      "exchange": "mexc",
      "mode": "single",
      "method": "fetchOrderBook",
      "symbols": [
        "CRO/USDT"
      ],
      "limit": null
    },
    {
      "exchange": "htx",
      "mode": "single",
      "method": "fetch_order_book",
      "symbols": [
        "DAI/USDT"
      ],
      "limit": null
    },
    {
      "exchange": "poloniex",
      "mode": "single",
      "method": "fetchOrderBook",
      "symbols": [
        "DOGE/USDT"
      ],
      "limit": null
    },
    {
      "exchange": "bitfinex2",
      "mode": "single",
      "method": "fetchOrderBook",
      "symbols": [
        "EGLD/USDT"
      ],
      "limit": null
    },
    {
      "exchange": "wazirx",
      "mode": "single",
      "method": "fetchOrderBook",
      "symbols": [
        "ENJ/USDT"
      ],
      "limit": null
    },
    {
      "exchange": "wazirx",
      "mode": "single",
      "method": "fetchOrderBook",
      "symbols": [
        "ETC/USDT"
      ],
      "limit": null
    },
    {
      "exchange": "woo",
      "mode": "single",
      "method": "fetchOrderBook",
      "symbols": [
        "ETHW/USDT"
      ],
      "limit": null
    },
    {
      "exchange": "bitrue",
      "mode": "single",
      "method": "fetchOrderBook",
      "symbols": [
        "FLR/USDT"
      ],
      "limit": null
    },
    {
      "exchange": "woo",
      "mode": "single",
      "method": "fetchOrderBook",
      "symbols": [
        "GALA/USDT"
      ],
      "limit": null
    },
    {
      "exchange": "bingx",
      "mode": "single",
      "method": "fetchOrderBook",
      "symbols": [
        "GRT/USDT"
      ],
      "limit": null
    },
    {
      "exchange": "htx",
      "mode": "single",
      "method": "fetch_order_book",
      "symbols": [
        "HOT/USDT"
      ],
      "limit": null
    },
    {
      "exchange": "bitrue",
      "mode": "single",
      "method": "fetchOrderBook",
      "symbols": [
        "INJ/USDT"
      ],
      "limit": null
    },
    {
      "exchange": "lbank",
      "mode": "single",
      "method": "fetchOrderBook",
      "symbols": [
        "JASMY/USDT"
      ],
      "limit": null
    },
    {
      "exchange": "wazirx",
      "mode": "single",
      "method": "fetchOrderBook",
      "symbols": [
        "KAVA/USDT"
      ],
      "limit": null
    },
    {
      "exchange": "whitebit",
      "mode": "single",
      "method": "fetchOrderBook",
      "symbols": [
        "LDO/USDT"
      ],
      "limit": null
    },
    {
      "exchange": "phemex",
      "mode": "single",
      "method": "fetchOrderBook",
      "symbols": [
        "LTC/USDT"
      ],
      "limit": null
    },
    {
      "exchange": "lbank",
      "mode": "single",
      "method": "fetchOrderBook",
      "symbols": [
        "MANTA/USDT"
      ],
      "limit": null
    },
    {
      "exchange": "poloniex",
      "mode": "single",
      "method": "fetchOrderBook",
      "symbols": [
        "METIS/USDT"
      ],
      "limit": null
    },
    {
      "exchange": "mexc",
      "mode": "single",
      "method": "fetchOrderBook",
      "symbols": [
        "MNT/USDT"
      ],
      "limit": null
    },
    {
      "exchange": "bitrue",
      "mode": "single",
      "method": "fetchOrderBook",
      "symbols": [
        "NEXO/USDT"
      ],
      "limit": null
    },
    {
      "exchange": "bitrue",
      "mode": "single",
      "method": "fetchOrderBook",
      "symbols": [
        "ONDO/USDT"
      ],
      "limit": null
    },
    {
      "exchange": "cex",
      "mode": "single",
      "method": "fetchOrderBook",
      "symbols": [
        "PAXG/USDT"
      ],
      "limit": null
    },
    {
      "exchange": "poloniex",
      "mode": "single",
      "method": "fetchOrderBook",
      "symbols": [
        "PONKE/USDT"
      ],
      "limit": null
    },
    {
      "exchange": "htx",
      "mode": "single",
      "method": "fetch_order_book",
      "symbols": [
        "QTUM/USDT"
      ],
      "limit": null
    },
    {
      "exchange": "currencycom",
      "mode": "single",
      "method": "fetchOrderBook",
      "symbols": [
        "RSR/USDT"
      ],
      "limit": null
    },
    {
      "exchange": "whitebit",
      "mode": "single",
      "method": "fetchOrderBook",
      "symbols": [
        "SAND/USDT"
      ],
      "limit": null
    },
    {
      "exchange": "currencycom",
      "mode": "single",
      "method": "fetchOrderBook",
      "symbols": [
        "SNX/USDT"
      ],
      "limit": null
    },
    {
      "exchange": "bingx",
      "mode": "single",
      "method": "fetchOrderBook",
      "symbols": [
        "STRK/USDT"
      ],
      "limit": null
    },
    {
      "exchange": "phemex",
      "mode": "single",
      "method": "fetchOrderBook",
      "symbols": [
        "T/USDT"
      ],
      "limit": null
    },
    {
      "exchange": "poloniex",
      "mode": "single",
      "method": "fetchOrderBook",
      "symbols": [
        "TRIBE/USDT"
      ],
      "limit": null
    },
    {
      "exchange": "mexc",
      "mode": "single",
      "method": "fetchOrderBook",
      "symbols": [
        "TWT/USDT"
      ],
      "limit": null
    },
    {
      "exchange": "mexc",
      "mode": "single",
      "method": "fetchOrderBook",
      "symbols": [
        "VENOM/USDT"
      ],
      "limit": null
    },
    {
      "exchange": "mexc",
      "mode": "single",
      "method": "fetchOrderBook",
      "symbols": [
        "WEMIX/USDT"
      ],
      "limit": null
    },
    {
      "exchange": "bitrue",
      "mode": "single",
      "method": "fetchOrderBook",
      "symbols": [
        "XDC/USDT"
      ],
      "limit": null
    },
    {
      "exchange": "ascendex",
      "mode": "single",
      "method": "fetchOrderBook",
      "symbols": [
        "XRD/USDT"
      ],
      "limit": null
    },
    {
      "exchange": "poloniex",
      "mode": "single",
      "method": "fetchOrderBook",
      "symbols": [
        "ZEC/USDT"
      ],
      "limit": null
    },
    {
      "exchange": "gate",
      "mode": "single",
      "method": "fetchOrderBook",
      "symbols": [
        "ZRO/USDT"
      ],
      "limit": null
    }
  ]
}