{
  "updater": [
    {
      "exchange": "bitmart",
      "mode": "batch",
      "symbols": [
        "HOOK/USDT",
        "METIS/USDT",
        "KAVA/USDT",
        "QANX/USDT",
        "WELSH/USDT",
        "ELF/USDT",
        "MODE/USDT",
        "HOT/USDT",
        "ALICE/USDT",
        "XCAD/USDT",
        "LTO/USDT",
        "TROLL/USDT",
        "IOST/USDT",
        "OP/USDT",
        "LINK/USDT",
        "TLM/USDT",
        "PSG/USDT",
        "KEY/USDT",
        "WXM/USDT",
        "WAGMIGAMES/USDT"
      ],
      "limit": 20,
      "method": "watchOrderBookForSymbols"
    },
    {
      "exchange": "coinbaseexchange",
      "mode": "batch",
      "symbols": [
        "C98/USDT",
        "API3/USDT",
        "MATH/USDT",
        "ARPA/USDT",
        "MDT/USDT",
        "MATIC/USDT",
        "POWR/USDT",
        "CRO/USDT",
        "SUPER/USDT",
        "BICO/USDT",
        "ATOM/USDT",
        "GALA/USDT",
        "XLM/USDT",
        "TRAC/USDT",
        "COVAL/USDT",
        "PERP/USDT",
        "AIOZ/USDT",
        "OP/USDT",
        "SPELL/USDT",
        "FOX/USDT",
        "GAL/USDT",
        "ZEN/USDT",
        "ENJ/USDT",
        "LRC/USDT",
        "POLY/USDT",
        "MINA/USDT",
        "DIA/USDT",
        "ALCX/USDT",
        "ENS/USDT",
        "AVAX/USDT",
        "FARM/USDT",
        "FET/USDT",
        "TRU/USDT",
        "NEAR/USDT",
        "POLS/USDT",
        "CTX/USDT",
        "DOT/USDT",
        "QNT/USDT",
        "KSM/USDT",
        "XYO/USDT",
        "CLV/USDT",
        "HBAR/USDT",
        "BOBA/USDT",
        "CHZ/USDT",
        "BTC/USDT",
        "LCX/USDT",
        "IMX/USDT",
        "WAMPL/USDT",
        "BOND/USDT",
        "FIDA/USDT",
        "APT/USDT",
        "RAD/USDT",
        "REQ/USDT",
        "FORT/USDT",
        "DOGE/USDT",
        "IDEX/USDT",
        "AXS/USDT",
        "ELA/USDT",
        "HOPR/USDT",
        "AGLD/USDT",
        "JASMY/USDT",
        "FIS/USDT",
        "KRL/USDT",
        "PRQ/USDT",
        "ATA/USDT",
        "ACH/USDT",
        "RLY/USDT",
        "ROSE/USDT",
        "MASK/USDT",
        "NCT/USDT",
        "LINK/USDT",
        "ETH/USDT",
        "POND/USDT",
        "BADGER/USDT",
        "LQTY/USDT",
        "ORN/USDT",
        "STG/USDT",
        "INDEX/USDT",
        "DESO/USDT",
        "ICP/USDT",
        "GMT/USDT",
        "VGX/USDT",
        "GNO/USDT",
        "SOL/USDT",
        "SUKU/USDT",
        "METIS/USDT",
        "XCN/USDT",
        "NEST/USDT",
        "RNDR/USDT",
        "AUCTION/USDT",
        "SAND/USDT"
      ],
      "limit": null,
      "method": "watchOrderBookForSymbols"
    },
    {
      "exchange": "probit",
      "mode": "single",
      "symbols": [
        "AAVE/USDT"
      ],
      "limit": null,
      "method": "fetchOrderBook"
    },
    {
      "exchange": "gate",
      "mode": "single",
      "symbols": [
        "AERGO/USDT"
      ],
      "limit": null,
      "method": "fetchOrderBook"
    },
    {
      "exchange": "probit",
      "mode": "single",
      "symbols": [
        "AGRS/USDT"
      ],
      "limit": null,
      "method": "fetchOrderBook"
    },
    {
      "exchange": "bitrue",
      "mode": "single",
      "symbols": [
        "ALGO/USDT"
      ],
      "limit": null,
      "method": "fetchOrderBook"
    },
    {
      "exchange": "mexc",
      "mode": "single",
      "symbols": [
        "ALPINE/USDT"
      ],
      "limit": null,
      "method": "fetchOrderBook"
    },
    {
      "exchange": "lbank",
      "mode": "single",
      "symbols": [
        "ANDY/USDT"
      ],
      "limit": null,
      "method": "fetchOrderBook"
    },
    {
      "exchange": "cex",
      "mode": "single",
      "symbols": [
        "APT/USDT"
      ],
      "limit": null,
      "method": "fetchOrderBook"
    },
    {
      "exchange": "poloniex",
      "mode": "single",
      "symbols": [
        "ARDR/USDT"
      ],
      "limit": null,
      "method": "fetchOrderBook"
    },
    {
      "exchange": "gate",
      "mode": "single",
      "symbols": [
        "AST/USDT"
      ],
      "limit": null,
      "method": "fetchOrderBook"
    },
    {
      "exchange": "lbank",
      "mode": "single",
      "symbols": [
        "ATOM/USDT"
      ],
      "limit": null,
      "method": "fetchOrderBook"
    },
    {
      "exchange": "ascendex",
      "mode": "single",
      "symbols": [
        "AVAX/USDT"
      ],
      "limit": null,
      "method": "fetchOrderBook"
    },
    {
      "exchange": "htx",
      "mode": "single",
      "symbols": [
        "AZERO/USDT"
      ],
      "limit": null,
      "method": "fetchOrderBook"
    },
    {
      "exchange": "poloniex",
      "mode": "single",
      "symbols": [
        "BAKE/USDT"
      ],
      "limit": null,
      "method": "fetchOrderBook"
    },
    {
      "exchange": "p2b",
      "mode": "single",
      "symbols": [
        "BAT/USDT"
      ],
      "limit": null,
      "method": "fetchOrderBook"
    },
    {
      "exchange": "p2b",
      "mode": "single",
      "symbols": [
        "BDX/USDT"
      ],
      "limit": null,
      "method": "fetchOrderBook"
    },
    {
      "exchange": "ascendex",
      "mode": "single",
      "symbols": [
        "BILLY/USDT"
      ],
      "limit": null,
      "method": "fetchOrderBook"
    },
    {
      "exchange": "gate",
      "mode": "single",
      "symbols": [
        "BMEX/USDT"
      ],
      "limit": null,
      "method": "fetchOrderBook"
    },
    {
      "exchange": "coinex",
      "mode": "single",
      "symbols": [
        "BOME/USDT"
      ],
      "limit": null,
      "method": "fetchOrderBook"
    },
    {
      "exchange": "coinex",
      "mode": "single",
      "symbols": [
        "BOZO/USDT"
      ],
      "limit": null,
      "method": "fetchOrderBook"
    },
    {
      "exchange": "mexc",
      "mode": "single",
      "symbols": [
        "BTC/USDT"
      ],
      "limit": null,
      "method": "fetchOrderBook"
    },
    {
      "exchange": "htx",
      "mode": "single",
      "symbols": [
        "C98/USDT"
      ],
      "limit": null,
      "method": "fetchOrderBook"
    },
    {
      "exchange": "bitrue",
      "mode": "single",
      "symbols": [
        "CEEK/USDT"
      ],
      "limit": null,
      "method": "fetchOrderBook"
    },
    {
      "exchange": "coinex",
      "mode": "single",
      "symbols": [
        "CFG/USDT"
      ],
      "limit": null,
      "method": "fetchOrderBook"
    },
    {
      "exchange": "gate",
      "mode": "single",
      "symbols": [
        "CHR/USDT"
      ],
      "limit": null,
      "method": "fetchOrderBook"
    },
    {
      "exchange": "bitrue",
      "mode": "single",
      "symbols": [
        "CLV/USDT"
      ],
      "limit": null,
      "method": "fetchOrderBook"
    },
    {
      "exchange": "mexc",
      "mode": "single",
      "symbols": [
        "COQ/USDT"
      ],
      "limit": null,
      "method": "fetchOrderBook"
    },
    {
      "exchange": "htx",
      "mode": "single",
      "symbols": [
        "CRO/USDT"
      ],
      "limit": null,
      "method": "fetchOrderBook"
    },
    {
      "exchange": "mexc",
      "mode": "single",
      "symbols": [
        "CSPR/USDT"
      ],
      "limit": null,
      "method": "fetchOrderBook"
    },
    {
      "exchange": "bitrue",
      "mode": "single",
      "symbols": [
        "CVC/USDT"
      ],
      "limit": null,
      "method": "fetchOrderBook"
    },
    {
      "exchange": "whitebit",
      "mode": "single",
      "symbols": [
        "DAI/USDT"
      ],
      "limit": null,
      "method": "fetchOrderBook"
    },
    {
      "exchange": "mexc",
      "mode": "single",
      "symbols": [
        "DCK/USDT"
      ],
      "limit": null,
      "method": "fetchOrderBook"
    },
    {
      "exchange": "phemex",
      "mode": "single",
      "symbols": [
        "DEXE/USDT"
      ],
      "limit": null,
      "method": "fetchOrderBook"
    },
    {
      "exchange": "mexc",
      "mode": "single",
      "symbols": [
        "DMAIL/USDT"
      ],
      "limit": null,
      "method": "fetchOrderBook"
    },
    {
      "exchange": "ascendex",
      "mode": "single",
      "symbols": [
        "DOT/USDT"
      ],
      "limit": null,
      "method": "fetchOrderBook"
    },
    {
      "exchange": "woo",
      "mode": "single",
      "symbols": [
        "DYDX/USDT"
      ],
      "limit": null,
      "method": "fetchOrderBook"
    },
    {
      "exchange": "phemex",
      "mode": "single",
      "symbols": [
        "ELF/USDT"
      ],
      "limit": null,
      "method": "fetchOrderBook"
    },
    {
      "exchange": "bitfinex2",
      "mode": "single",
      "symbols": [
        "EOS/USDT"
      ],
      "limit": null,
      "method": "fetchOrderBook"
    },
    {
      "exchange": "ascendex",
      "mode": "single",
      "symbols": [
        "ETH/USDT"
      ],
      "limit": null,
      "method": "fetchOrderBook"
    },
    {
      "exchange": "woo",
      "mode": "single",
      "symbols": [
        "ETHW/USDT"
      ],
      "limit": null,
      "method": "fetchOrderBook"
    },
    {
      "exchange": "mexc",
      "mode": "single",
      "symbols": [
        "FEG/USDT"
      ],
      "limit": null,
      "method": "fetchOrderBook"
    },
    {
      "exchange": "gate",
      "mode": "single",
      "symbols": [
        "FIO/USDT"
      ],
      "limit": null,
      "method": "fetchOrderBook"
    },
    {
      "exchange": "wazirx",
      "mode": "single",
      "symbols": [
        "FLOKI/USDT"
      ],
      "limit": null,
      "method": "fetchOrderBook"
    },
    {
      "exchange": "bitrue",
      "mode": "single",
      "symbols": [
        "FRAX/USDT"
      ],
      "limit": null,
      "method": "fetchOrderBook"
    },
    {
      "exchange": "ascendex",
      "mode": "single",
      "symbols": [
        "FUSE/USDT"
      ],
      "limit": null,
      "method": "fetchOrderBook"
    },
    {
      "exchange": "whitebit",
      "mode": "single",
      "symbols": [
        "GALA/USDT"
      ],
      "limit": null,
      "method": "fetchOrderBook"
    },
    {
      "exchange": "gate",
      "mode": "single",
      "symbols": [
        "GLM/USDT"
      ],
      "limit": null,
      "method": "fetchOrderBook"
    },
    {
      "exchange": "mexc",
      "mode": "single",
      "symbols": [
        "GMX/USDT"
      ],
      "limit": null,
      "method": "fetchOrderBook"
    },
    {
      "exchange": "coinex",
      "mode": "single",
      "symbols": [
        "GPU/USDT"
      ],
      "limit": null,
      "method": "fetchOrderBook"
    },
    {
      "exchange": "mexc",
      "mode": "single",
      "symbols": [
        "HAPI/USDT"
      ],
      "limit": null,
      "method": "fetchOrderBook"
    },
    {
      "exchange": "phemex",
      "mode": "single",
      "symbols": [
        "HIFI/USDT"
      ],
      "limit": null,
      "method": "fetchOrderBook"
    },
    {
      "exchange": "currencycom",
      "mode": "single",
      "symbols": [
        "HOT/USDT"
      ],
      "limit": null,
      "method": "fetchOrderBook"
    },
    {
      "exchange": "mexc",
      "mode": "single",
      "symbols": [
        "ICP/USDT"
      ],
      "limit": null,
      "method": "fetchOrderBook"
    },
    {
      "exchange": "ascendex",
      "mode": "single",
      "symbols": [
        "IMX/USDT"
      ],
      "limit": null,
      "method": "fetchOrderBook"
    },
    {
      "exchange": "gate",
      "mode": "single",
      "symbols": [
        "IO/USDT"
      ],
      "limit": null,
      "method": "fetchOrderBook"
    },
    {
      "exchange": "probit",
      "mode": "single",
      "symbols": [
        "ISK/USDT"
      ],
      "limit": null,
      "method": "fetchOrderBook"
    },
    {
      "exchange": "wazirx",
      "mode": "single",
      "symbols": [
        "JST/USDT"
      ],
      "limit": null,
      "method": "fetchOrderBook"
    },
    {
      "exchange": "poloniex",
      "mode": "single",
      "symbols": [
        "KAS/USDT"
      ],
      "limit": null,
      "method": "fetchOrderBook"
    },
    {
      "exchange": "lbank",
      "mode": "single",
      "symbols": [
        "KIMBO/USDT"
      ],
      "limit": null,
      "method": "fetchOrderBook"
    },
    {
      "exchange": "mexc",
      "mode": "single",
      "symbols": [
        "KNC/USDT"
      ],
      "limit": null,
      "method": "fetchOrderBook"
    },
    {
      "exchange": "gate",
      "mode": "single",
      "symbols": [
        "LADYS/USDT"
      ],
      "limit": null,
      "method": "fetchOrderBook"
    },
    {
      "exchange": "mexc",
      "mode": "single",
      "symbols": [
        "LEVER/USDT"
      ],
      "limit": null,
      "method": "fetchOrderBook"
    },
    {
      "exchange": "lbank",
      "mode": "single",
      "symbols": [
        "LIXX/USDT"
      ],
      "limit": null,
      "method": "fetchOrderBook"
    },
    {
      "exchange": "wazirx",
      "mode": "single",
      "symbols": [
        "LOVELY/USDT"
      ],
      "limit": null,
      "method": "fetchOrderBook"
    },
    {
      "exchange": "bitfinex2",
      "mode": "single",
      "symbols": [
        "LTC/USDT"
      ],
      "limit": null,
      "method": "fetchOrderBook"
    },
    {
      "exchange": "gate",
      "mode": "single",
      "symbols": [
        "LUNR/USDT"
      ],
      "limit": null,
      "method": "fetchOrderBook"
    },
    {
      "exchange": "ascendex",
      "mode": "single",
      "symbols": [
        "MANTA/USDT"
      ],
      "limit": null,
      "method": "fetchOrderBook"
    },
    {
      "exchange": "phemex",
      "mode": "single",
      "symbols": [
        "MATIC/USDT"
      ],
      "limit": null,
      "method": "fetchOrderBook"
    },
    {
      "exchange": "gate",
      "mode": "single",
      "symbols": [
        "MDT/USDT"
      ],
      "limit": null,
      "method": "fetchOrderBook"
    },
    {
      "exchange": "coinex",
      "mode": "single",
      "symbols": [
        "MEW/USDT"
      ],
      "limit": null,
      "method": "fetchOrderBook"
    },
    {
      "exchange": "coinex",
      "mode": "single",
      "symbols": [
        "MKR/USDT"
      ],
      "limit": null,
      "method": "fetchOrderBook"
    },
    {
      "exchange": "gate",
      "mode": "single",
      "symbols": [
        "MOBILE/USDT"
      ],
      "limit": null,
      "method": "fetchOrderBook"
    },
    {
      "exchange": "gate",
      "mode": "single",
      "symbols": [
        "MTL/USDT"
      ],
      "limit": null,
      "method": "fetchOrderBook"
    },
    {
      "exchange": "gate",
      "mode": "single",
      "symbols": [
        "NAVX/USDT"
      ],
      "limit": null,
      "method": "fetchOrderBook"
    },
    {
      "exchange": "gate",
      "mode": "single",
      "symbols": [
        "NEON/USDT"
      ],
      "limit": null,
      "method": "fetchOrderBook"
    },
    {
      "exchange": "phemex",
      "mode": "single",
      "symbols": [
        "NMR/USDT"
      ],
      "limit": null,
      "method": "fetchOrderBook"
    },
    {
      "exchange": "mexc",
      "mode": "single",
      "symbols": [
        "NULS/USDT"
      ],
      "limit": null,
      "method": "fetchOrderBook"
    },
    {
      "exchange": "htx",
      "mode": "single",
      "symbols": [
        "OCT/USDT"
      ],
      "limit": null,
      "method": "fetchOrderBook"
    },
    {
      "exchange": "poloniex",
      "mode": "single",
      "symbols": [
        "OM/USDT"
      ],
      "limit": null,
      "method": "fetchOrderBook"
    },
    {
      "exchange": "coinex",
      "mode": "single",
      "symbols": [
        "OOKI/USDT"
      ],
      "limit": null,
      "method": "fetchOrderBook"
    },
    {
      "exchange": "poloniex",
      "mode": "single",
      "symbols": [
        "ORCA/USDT"
      ],
      "limit": null,
      "method": "fetchOrderBook"
    },
    {
      "exchange": "gate",
      "mode": "single",
      "symbols": [
        "OXT/USDT"
      ],
      "limit": null,
      "method": "fetchOrderBook"
    },
    {
      "exchange": "htx",
      "mode": "single",
      "symbols": [
        "PENDLE/USDT"
      ],
      "limit": null,
      "method": "fetchOrderBook"
    },
    {
      "exchange": "whitebit",
      "mode": "single",
      "symbols": [
        "PHA/USDT"
      ],
      "limit": null,
      "method": "fetchOrderBook"
    },
    {
      "exchange": "coinex",
      "mode": "single",
      "symbols": [
        "PNK/USDT"
      ],
      "limit": null,
      "method": "fetchOrderBook"
    },
    {
      "exchange": "wazirx",
      "mode": "single",
      "symbols": [
        "POND/USDT"
      ],
      "limit": null,
      "method": "fetchOrderBook"
    },
    {
      "exchange": "lbank",
      "mode": "single",
      "symbols": [
        "PORTAL/USDT"
      ],
      "limit": null,
      "method": "fetchOrderBook"
    },
    {
      "exchange": "mexc",
      "mode": "single",
      "symbols": [
        "PRQ/USDT"
      ],
      "limit": null,
      "method": "fetchOrderBook"
    },
    {
      "exchange": "poloniex",
      "mode": "single",
      "symbols": [
        "PYR/USDT"
      ],
      "limit": null,
      "method": "fetchOrderBook"
    },
    {
      "exchange": "lbank",
      "mode": "single",
      "symbols": [
        "QTUM/USDT"
      ],
      "limit": null,
      "method": "fetchOrderBook"
    },
    {
      "exchange": "bitrue",
      "mode": "single",
      "symbols": [
        "RAY/USDT"
      ],
      "limit": null,
      "method": "fetchOrderBook"
    },
    {
      "exchange": "cex",
      "mode": "single",
      "symbols": [
        "REN/USDT"
      ],
      "limit": null,
      "method": "fetchOrderBook"
    },
    {
      "exchange": "gate",
      "mode": "single",
      "symbols": [
        "RLC/USDT"
      ],
      "limit": null,
      "method": "fetchOrderBook"
    },
    {
      "exchange": "bitrue",
      "mode": "single",
      "symbols": [
        "RSR/USDT"
      ],
      "limit": null,
      "method": "fetchOrderBook"
    },
    {
      "exchange": "coinex",
      "mode": "single",
      "symbols": [
        "RXD/USDT"
      ],
      "limit": null,
      "method": "fetchOrderBook"
    },
    {
      "exchange": "gate",
      "mode": "single",
      "symbols": [
        "SATS/USDT"
      ],
      "limit": null,
      "method": "fetchOrderBook"
    },
    {
      "exchange": "mexc",
      "mode": "single",
      "symbols": [
        "SDEX/USDT"
      ],
      "limit": null,
      "method": "fetchOrderBook"
    },
    {
      "exchange": "lbank",
      "mode": "single",
      "symbols": [
        "SHDW/USDT"
      ],
      "limit": null,
      "method": "fetchOrderBook"
    },
    {
      "exchange": "ascendex",
      "mode": "single",
      "symbols": [
        "SLIM/USDT"
      ],
      "limit": null,
      "method": "fetchOrderBook"
    },
    {
      "exchange": "gate",
      "mode": "single",
      "symbols": [
        "SNX/USDT"
      ],
      "limit": null,
      "method": "fetchOrderBook"
    },
    {
      "exchange": "phemex",
      "mode": "single",
      "symbols": [
        "SPA/USDT"
      ],
      "limit": null,
      "method": "fetchOrderBook"
    },
    {
      "exchange": "gate",
      "mode": "single",
      "symbols": [
        "STBU/USDT"
      ],
      "limit": null,
      "method": "fetchOrderBook"
    },
    {
      "exchange": "phemex",
      "mode": "single",
      "symbols": [
        "STORJ/USDT"
      ],
      "limit": null,
      "method": "fetchOrderBook"
    },
    {
      "exchange": "bitfinex2",
      "mode": "single",
      "symbols": [
        "SUI/USDT"
      ],
      "limit": null,
      "method": "fetchOrderBook"
    },
    {
      "exchange": "bitrue",
      "mode": "single",
      "symbols": [
        "SUSHI/USDT"
      ],
      "limit": null,
      "method": "fetchOrderBook"
    },
    {
      "exchange": "poloniex",
      "mode": "single",
      "symbols": [
        "SXP/USDT"
      ],
      "limit": null,
      "method": "fetchOrderBook"
    },
    {
      "exchange": "gate",
      "mode": "single",
      "symbols": [
        "TAO/USDT"
      ],
      "limit": null,
      "method": "fetchOrderBook"
    },
    {
      "exchange": "mexc",
      "mode": "single",
      "symbols": [
        "TKO/USDT"
      ],
      "limit": null,
      "method": "fetchOrderBook"
    },
    {
      "exchange": "bitfinex",
      "mode": "single",
      "symbols": [
        "TOMI/USDT"
      ],
      "limit": null,
      "method": "fetchOrderBook"
    },
    {
      "exchange": "poloniex",
      "mode": "single",
      "symbols": [
        "TREMP/USDT"
      ],
      "limit": null,
      "method": "fetchOrderBook"
    },
    {
      "exchange": "phemex",
      "mode": "single",
      "symbols": [
        "TRX/USDT"
      ],
      "limit": null,
      "method": "fetchOrderBook"
    },
    {
      "exchange": "wazirx",
      "mode": "single",
      "symbols": [
        "TWT/USDT"
      ],
      "limit": null,
      "method": "fetchOrderBook"
    },
    {
      "exchange": "currencycom",
      "mode": "single",
      "symbols": [
        "UNI/USDT"
      ],
      "limit": null,
      "method": "fetchOrderBook"
    },
    {
      "exchange": "htx",
      "mode": "single",
      "symbols": [
        "USDP/USDT"
      ],
      "limit": null,
      "method": "fetchOrderBook"
    },
    {
      "exchange": "wazirx",
      "mode": "single",
      "symbols": [
        "VET/USDT"
      ],
      "limit": null,
      "method": "fetchOrderBook"
    },
    {
      "exchange": "htx",
      "mode": "single",
      "symbols": [
        "VOXEL/USDT"
      ],
      "limit": null,
      "method": "fetchOrderBook"
    },
    {
      "exchange": "mexc",
      "mode": "single",
      "symbols": [
        "W/USDT"
      ],
      "limit": null,
      "method": "fetchOrderBook"
    },
    {
      "exchange": "gate",
      "mode": "single",
      "symbols": [
        "WEETH/USDT"
      ],
      "limit": null,
      "method": "fetchOrderBook"
    },
    {
      "exchange": "bitrue",
      "mode": "single",
      "symbols": [
        "WLD/USDT"
      ],
      "limit": null,
      "method": "fetchOrderBook"
    },
    {
      "exchange": "woo",
      "mode": "single",
      "symbols": [
        "WOO/USDT"
      ],
      "limit": null,
      "method": "fetchOrderBook"
    },
    {
      "exchange": "poloniex",
      "mode": "single",
      "symbols": [
        "XCAD/USDT"
      ],
      "limit": null,
      "method": "fetchOrderBook"
    },
    {
      "exchange": "htx",
      "mode": "single",
      "symbols": [
        "XEM/USDT"
      ],
      "limit": null,
      "method": "fetchOrderBook"
    },
    {
      "exchange": "coinex",
      "mode": "single",
      "symbols": [
        "XPLA/USDT"
      ],
      "limit": null,
      "method": "fetchOrderBook"
    },
    {
      "exchange": "mexc",
      "mode": "single",
      "symbols": [
        "XVS/USDT"
      ],
      "limit": null,
      "method": "fetchOrderBook"
    },
    {
      "exchange": "wazirx",
      "mode": "single",
      "symbols": [
        "YGG/USDT"
      ],
      "limit": null,
      "method": "fetchOrderBook"
    },
    {
      "exchange": "coinex",
      "mode": "single",
      "symbols": [
        "ZEUS/USDT"
      ],
      "limit": null,
      "method": "fetchOrderBook"
    },
    {
      "exchange": "coinex",
      "mode": "single",
      "symbols": [
        "ZKF/USDT"
      ],
      "limit": null,
      "method": "fetchOrderBook"
    }
  ]
}