{
  "dealer": {
    "symbols": {
      "FLOKI/USDT": [
        "ascendex",
        "binance",
        "bingx",
        "bitfinex2",
        "bitget",
        "bitmart",
        "bitrue",
        "bybit",
        "cryptocom",
        "gate",
        "hitbtc",
        "htx",
        "kucoin",
        "lbank",
        "okx",
        "poloniex",
        "wazirx",
        "whitebit"
      ],
      "HNT/USDT": [
        "bingx",
        "bitget",
        "bitmart",
        "bitrue",
        "bybit",
        "cryptocom",
        "gate",
        "kucoin",
        "poloniex",
        "wazirx"
      ],
      "BLUR/USDT": [
        "ascendex",
        "binance",
        "bingx",
        "bitfinex2",
        "bitget",
        "bitmart",
        "bitrue",
        "bybit",
        "cryptocom",
        "gate",
        "hitbtc",
        "htx",
        "kucoin",
        "lbank",
        "okx",
        "phemex",
        "poloniex",
        "wazirx",
        "whitebit"
      ],
      "T/USDT": [
        "binance",
        "bingx",
        "bitget",
        "bitmart",
        "bitrue",
        "bybit",
        "cryptocom",
        "gate",
        "hitbtc",
        "htx",
        "kucoin",
        "lbank",
        "okx",
        "phemex",
        "poloniex",
        "probit",
        "wazirx",
        "whitebit"
      ]
    }
  },
  "updater": [
    {
      "exchange": "whitebit",
      "mode": "single",
      "method": "fetchOrderBook",
      "symbols": [
        "1INCH/USDT"
      ],
      "limit": null
    },
    {
      "exchange": "lbank",
      "mode": "single",
      "method": "fetchOrderBook",
      "symbols": [
        "ALGO/USDT"
      ],
      "limit": null
    },
    {
      "exchange": "wazirx",
      "mode": "single",
      "method": "fetchOrderBook",
      "symbols": [
        "API3/USDT"
      ],
      "limit": null
    },
    {
      "exchange": "mexc",
      "mode": "single",
      "method": "fetchOrderBook",
      "symbols": [
        "ASTR/USDT"
      ],
      "limit": null
    },
    {
      "exchange": "poloniex",
      "mode": "single",
      "method": "fetchOrderBook",
      "symbols": [
        "AXS/USDT"
      ],
      "limit": null
    },
    {
      "exchange": "bitfinex2",
      "mode": "single",
      "method": "fetchOrderBook",
      "symbols": [
        "BLUR/USDT"
      ],
      "limit": null
    },
    {
      "exchange": "lbank",
      "mode": "single",
      "method": "fetchOrderBook",
      "symbols": [
        "BTC/USDT"
      ],
      "limit": null
    },
    {
      "exchange": "bitrue",
      "mode": "single",
      "method": "fetchOrderBook",
      "symbols": [
        "CHZ/USDT"
      ],
      "limit": null
    },
    {
      "exchange": "lbank",
      "mode": "single",
      "method": "fetchOrderBook",
      "symbols": [
        "CRO/USDT"
      ],
      "limit": null
    },
    {
      "exchange": "htx",
      "mode": "single",
      "method": "fetchOrderBook",
      "symbols": [
        "DASH/USDT"
      ],
      "limit": null
    },
    {
      "exchange": "bingx",
      "mode": "single",
      "method": "fetchOrderBook",
      "symbols": [
        "DYDX/USDT"
      ],
      "limit": null
    },
    {
      "exchange": "ascendex",
      "mode": "single",
      "method": "fetchOrderBook",
      "symbols": [
        "ENJ/USDT"
      ],
      "limit": null
    },
    {
      "exchange": "probit",
      "mode": "single",
      "method": "fetchOrderBook",
      "symbols": [
        "ETC/USDT"
      ],
      "limit": null
    },
    {
      "exchange": "lbank",
      "mode": "single",
      "method": "fetchOrderBook",
      "symbols": [
        "FET/USDT"
      ],
      "limit": null
    },
    {
      "exchange": "poloniex",
      "mode": "single",
      "method": "fetchOrderBook",
      "symbols": [
        "FTM/USDT"
      ],
      "limit": null
    },
    {
      "exchange": "probit",
      "mode": "single",
      "method": "fetchOrderBook",
      "symbols": [
        "GMX/USDT"
      ],
      "limit": null
    },
    {
      "exchange": "gate",
      "mode": "single",
      "method": "fetchOrderBook",
      "symbols": [
        "HOT/USDT"
      ],
      "limit": null
    },
    {
      "exchange": "ascendex",
      "mode": "single",
      "method": "fetchOrderBook",
      "symbols": [
        "IO/USDT"
      ],
      "limit": null
    },
    {
      "exchange": "phemex",
      "mode": "single",
      "method": "fetchOrderBook",
      "symbols": [
        "JTO/USDT"
      ],
      "limit": null
    },
    {
      "exchange": "bitrue",
      "mode": "single",
      "method": "fetchOrderBook",
      "symbols": [
        "LDO/USDT"
      ],
      "limit": null
    },
    {
      "exchange": "probit",
      "mode": "single",
      "method": "fetchOrderBook",
      "symbols": [
        "LTC/USDT"
      ],
      "limit": null
    },
    {
      "exchange": "whitebit",
      "mode": "single",
      "method": "fetchOrderBook",
      "symbols": [
        "MASK/USDT"
      ],
      "limit": null
    },
    {
      "exchange": "cryptocom",
      "mode": "single",
      "method": "fetchOrderBook",
      "symbols": [
        "MKR/USDT"
      ],
      "limit": null
    },
    {
      "exchange": "probit",
      "mode": "single",
      "method": "fetchOrderBook",
      "symbols": [
        "NEO/USDT"
      ],
      "limit": null
    },
    {
      "exchange": "gate",
      "mode": "single",
      "method": "fetchOrderBook",
      "symbols": [
        "OP/USDT"
      ],
      "limit": null
    },
    {
      "exchange": "lbank",
      "mode": "single",
      "method": "fetchOrderBook",
      "symbols": [
        "PEPECOIN/USDT"
      ],
      "limit": null
    },
    {
      "exchange": "ascendex",
      "mode": "single",
      "method": "fetchOrderBook",
      "symbols": [
        "QTUM/USDT"
      ],
      "limit": null
    },
    {
      "exchange": "phemex",
      "mode": "single",
      "method": "fetchOrderBook",
      "symbols": [
        "RUNE/USDT"
      ],
      "limit": null
    },
    {
      "exchange": "phemex",
      "mode": "single",
      "method": "fetchOrderBook",
      "symbols": [
        "SFP/USDT"
      ],
      "limit": null
    },
    {
      "exchange": "whitebit",
      "mode": "single",
      "method": "fetchOrderBook",
      "symbols": [
        "SSV/USDT"
      ],
      "limit": null
    },
    {
      "exchange": "probit",
      "mode": "single",
      "method": "fetchOrderBook",
      "symbols": [
        "T/USDT"
      ],
      "limit": null
    },
    {
      "exchange": "phemex",
      "mode": "single",
      "method": "fetchOrderBook",
      "symbols": [
        "TRX/USDT"
      ],
      "limit": null
    },
    {
      "exchange": "gate",
      "mode": "single",
      "method": "fetchOrderBook",
      "symbols": [
        "USDC/USDT"
      ],
      "limit": null
    },
    {
      "exchange": "phemex",
      "mode": "single",
      "method": "fetchOrderBook",
      "symbols": [
        "WBTC/USDT"
      ],
      "limit": null
    },
    {
      "exchange": "lbank",
      "mode": "single",
      "method": "fetchOrderBook",
      "symbols": [
        "XDC/USDT"
      ],
      "limit": null
    },
    {
      "exchange": "wazirx",
      "mode": "single",
      "method": "fetchOrderBook",
      "symbols": [
        "XTZ/USDT"
      ],
      "limit": null
    },
    {
      "exchange": "htx",
      "mode": "single",
      "method": "fetchOrderBook",
      "symbols": [
        "ZIL/USDT"
      ],
      "limit": null
    }
  ]
}